RsOsp/RsOsp.py
RsOsp/__init__.py
RsOsp/enums.py
RsOsp/repcap.py
RsOsp/CustomFiles/__init__.py
RsOsp/CustomFiles/events.py
RsOsp/CustomFiles/utilities.py
RsOsp/Implementations/Configure.py
RsOsp/Implementations/Diagnostic.py
RsOsp/Implementations/Read.py
RsOsp/Implementations/Route.py
RsOsp/Implementations/Trigger.py
RsOsp/Implementations/__init__.py
RsOsp/Implementations/Configure_/All.py
RsOsp/Implementations/Configure_/Compatible.py
RsOsp/Implementations/Configure_/Frame.py
RsOsp/Implementations/Configure_/Lock.py
RsOsp/Implementations/Configure_/MainInfo.py
RsOsp/Implementations/Configure_/PowerUp.py
RsOsp/Implementations/Configure_/Relay.py
RsOsp/Implementations/Configure_/Virtual.py
RsOsp/Implementations/Configure_/__init__.py
RsOsp/Implementations/Configure_/All_/Restore.py
RsOsp/Implementations/Configure_/All_/__init__.py
RsOsp/Implementations/Configure_/All_/Restore_/Catalog.py
RsOsp/Implementations/Configure_/All_/Restore_/__init__.py
RsOsp/Implementations/Configure_/Frame_/Define.py
RsOsp/Implementations/Configure_/Frame_/ImportPy.py
RsOsp/Implementations/Configure_/Frame_/Insert.py
RsOsp/Implementations/Configure_/Frame_/__init__.py
RsOsp/Implementations/Configure_/Frame_/ImportPy_/Catalog.py
RsOsp/Implementations/Configure_/Frame_/ImportPy_/__init__.py
RsOsp/Implementations/Configure_/Relay_/Delay.py
RsOsp/Implementations/Configure_/Relay_/__init__.py
RsOsp/Implementations/Diagnostic_/Service.py
RsOsp/Implementations/Diagnostic_/__init__.py
RsOsp/Implementations/Diagnostic_/Service_/Module.py
RsOsp/Implementations/Diagnostic_/Service_/User.py
RsOsp/Implementations/Diagnostic_/Service_/__init__.py
RsOsp/Implementations/Diagnostic_/Service_/Module_/Function.py
RsOsp/Implementations/Diagnostic_/Service_/Module_/HwInfo.py
RsOsp/Implementations/Diagnostic_/Service_/Module_/Temperature.py
RsOsp/Implementations/Diagnostic_/Service_/Module_/__init__.py
RsOsp/Implementations/Read_/Io.py
RsOsp/Implementations/Read_/Module.py
RsOsp/Implementations/Read_/Relay.py
RsOsp-2.10.17.75.dist-info/METADATA
RsOsp-2.10.17.75.dist-info/WHEEL
RsOsp-2.10.17.75.dist-info/top_level.txt
RsOsp-2.10.17.75.dist-info/RECORD
