Metadata-Version: 2.1
Name: RsOsp
Version: 2.10.17.75
Summary: OSP Opens Switch Platform Remote-control Module
Home-page: UNKNOWN
Author: Rohde & Schwarz GmbH & Co. KG
Author-email: Customer.Support@rohde-schwarz.com
License: MIT
Platform: UNKNOWN
Classifier: License :: OSI Approved :: MIT License
Classifier: Programming Language :: Python :: 3.6
Requires-Dist: PyVisa
